docgenerator/__init__.py
docgenerator/command_line.py
helpers/__init__.py
helpers/logger.py
helpers/settings.py
lib/__init__.py
lib/apps_oper.py
lib/desc_oper.py
lib/file_oper.py
lib/services_oper.py
lib/volumes_oper.py
tests/__init__.py
docgenerator-1.0.3.dist-info/LICENSE
docgenerator-1.0.3.dist-info/METADATA
docgenerator-1.0.3.dist-info/WHEEL
docgenerator-1.0.3.dist-info/entry_points.txt
docgenerator-1.0.3.dist-info/top_level.txt
docgenerator-1.0.3.dist-info/RECORD
