Metadata-Version: 2.1
Name: docgenerator
Version: 1.0.3
Summary: Tooling for generating documentation from Helm Charts
Home-page: https://github.com/truecharts/DocGenerator
Author-email: into@truecharts.org
License: UNKNOWN
Platform: UNKNOWN
Requires-Dist: ruamel.yaml
Requires-Dist: py-markdown-table
